[
  {
    "fecha": "2025-07-27",
    "llamadas_diarias": 319,
    "tmo_diario": 289.8244514106583
  },
  {
    "fecha": "2025-07-28",
    "llamadas_diarias": 2504,
    "tmo_diario": 341.1968849840256
  },
  {
    "fecha": "2025-07-29",
    "llamadas_diarias": 2742,
    "tmo_diario": 343.04996353026985
  },
  {
    "fecha": "2025-07-30",
    "llamadas_diarias": 2901,
    "tmo_diario": 341.7749052051017
  },
  {
    "fecha": "2025-07-31",
    "llamadas_diarias": 3002,
    "tmo_diario": 337.96502331778817
  },
  {
    "fecha": "2025-08-01",
    "llamadas_diarias": 2302,
    "tmo_diario": 336.56255430060816
  },
  {
    "fecha": "2025-08-02",
    "llamadas_diarias": 1369,
    "tmo_diario": 313.7355734112491
  },
  {
    "fecha": "2025-08-03",
    "llamadas_diarias": 858,
    "tmo_diario": 308.8240093240093
  },
  {
    "fecha": "2025-08-04",
    "llamadas_diarias": 1959,
    "tmo_diario": 351.60183767228176
  },
  {
    "fecha": "2025-08-05",
    "llamadas_diarias": 2069,
    "tmo_diario": 342.23876268728856
  },
  {
    "fecha": "2025-08-06",
    "llamadas_diarias": 2008,
    "tmo_diario": 341.49402390438246
  },
  {
    "fecha": "2025-08-07",
    "llamadas_diarias": 2055,
    "tmo_diario": 336.53722627737227
  },
  {
    "fecha": "2025-08-08",
    "llamadas_diarias": 1930,
    "tmo_diario": 338.3559585492228
  },
  {
    "fecha": "2025-08-09",
    "llamadas_diarias": 1418,
    "tmo_diario": 315.49576868829337
  },
  {
    "fecha": "2025-08-10",
    "llamadas_diarias": 919,
    "tmo_diario": 309.81066376496193
  },
  {
    "fecha": "2025-08-11",
    "llamadas_diarias": 2001,
    "tmo_diario": 352.14692653673166
  },
  {
    "fecha": "2025-08-12",
    "llamadas_diarias": 2106,
    "tmo_diario": 342.4738841405508
  },
  {
    "fecha": "2025-08-13",
    "llamadas_diarias": 2049,
    "tmo_diario": 341.7969741337238
  },
  {
    "fecha": "2025-08-14",
    "llamadas_diarias": 2084,
    "tmo_diario": 336.7735124760077
  },
  {
    "fecha": "2025-08-15",
    "llamadas_diarias": 978,
    "tmo_diario": 310.57055214723925
  },
  {
    "fecha": "2025-08-16",
    "llamadas_diarias": 1343,
    "tmo_diario": 316.3581533879375
  },
  {
    "fecha": "2025-08-17",
    "llamadas_diarias": 888,
    "tmo_diario": 309.911036036036
  },
  {
    "fecha": "2025-08-18",
    "llamadas_diarias": 2020,
    "tmo_diario": 352.139603960396
  },
  {
    "fecha": "2025-08-19",
    "llamadas_diarias": 2126,
    "tmo_diario": 342.5555032925682
  },
  {
    "fecha": "2025-08-20",
    "llamadas_diarias": 2068,
    "tmo_diario": 341.8133462282398
  },
  {
    "fecha": "2025-08-21",
    "llamadas_diarias": 2100,
    "tmo_diario": 336.85761904761904
  },
  {
    "fecha": "2025-08-22",
    "llamadas_diarias": 1948,
    "tmo_diario": 338.60420944558524
  },
  {
    "fecha": "2025-08-23",
    "llamadas_diarias": 1418,
    "tmo_diario": 315.5860366713681
  },
  {
    "fecha": "2025-08-24",
    "llamadas_diarias": 918,
    "tmo_diario": 309.83660130718954
  },
  {
    "fecha": "2025-08-25",
    "llamadas_diarias": 1998,
    "tmo_diario": 352.15215215215215
  },
  {
    "fecha": "2025-08-26",
    "llamadas_diarias": 2104,
    "tmo_diario": 342.5499049429658
  },
  {
    "fecha": "2025-08-27",
    "llamadas_diarias": 2047,
    "tmo_diario": 341.8549096238398
  },
  {
    "fecha": "2025-08-28",
    "llamadas_diarias": 2082,
    "tmo_diario": 336.8578290105668
  },
  {
    "fecha": "2025-08-29",
    "llamadas_diarias": 1937,
    "tmo_diario": 338.60196179659266
  },
  {
    "fecha": "2025-08-30",
    "llamadas_diarias": 1413,
    "tmo_diario": 315.5916489738146
  },
  {
    "fecha": "2025-08-31",
    "llamadas_diarias": 918,
    "tmo_diario": 309.83660130718954
  },
  {
    "fecha": "2025-09-01",
    "llamadas_diarias": 1918,
    "tmo_diario": 350.9337851929093
  },
  {
    "fecha": "2025-09-02",
    "llamadas_diarias": 2101,
    "tmo_diario": 347.6744407425036
  },
  {
    "fecha": "2025-09-03",
    "llamadas_diarias": 2114,
    "tmo_diario": 342.1773888363292
  },
  {
    "fecha": "2025-09-04",
    "llamadas_diarias": 2217,
    "tmo_diario": 341.2665764546685
  },
  {
    "fecha": "2025-09-05",
    "llamadas_diarias": 2252,
    "tmo_diario": 341.84458259325044
  },
  {
    "fecha": "2025-09-06",
    "llamadas_diarias": 1708,
    "tmo_diario": 321.7453161592506
  },
  {
    "fecha": "2025-09-07",
    "llamadas_diarias": 1181,
    "tmo_diario": 315.98814563928875
  },
  {
    "fecha": "2025-09-08",
    "llamadas_diarias": 2019,
    "tmo_diario": 352.37989103516594
  },
  {
    "fecha": "2025-09-09",
    "llamadas_diarias": 2099,
    "tmo_diario": 348.1400666984278
  },
  {
    "fecha": "2025-09-10",
    "llamadas_diarias": 2076,
    "tmo_diario": 342.2013487475915
  },
  {
    "fecha": "2025-09-11",
    "llamadas_diarias": 2168,
    "tmo_diario": 341.2320110701107
  },
  {
    "fecha": "2025-09-12",
    "llamadas_diarias": 2205,
    "tmo_diario": 341.99410430839004
  },
  {
    "fecha": "2025-09-13",
    "llamadas_diarias": 1656,
    "tmo_diario": 321.64915458937196
  },
  {
    "fecha": "2025-09-14",
    "llamadas_diarias": 1112,
    "tmo_diario": 316.0386690647482
  },
  {
    "fecha": "2025-09-15",
    "llamadas_diarias": 1992,
    "tmo_diario": 352.4874497991968
  },
  {
    "fecha": "2025-09-16",
    "llamadas_diarias": 2103,
    "tmo_diario": 348.23918212077984
  },
  {
    "fecha": "2025-09-17",
    "llamadas_diarias": 2089,
    "tmo_diario": 342.44710387745334
  },
  {
    "fecha": "2025-09-18",
    "llamadas_diarias": 1494,
    "tmo_diario": 310.3580990629183
  },
  {
    "fecha": "2025-09-19",
    "llamadas_diarias": 1397,
    "tmo_diario": 310.73085182534004
  },
  {
    "fecha": "2025-09-20",
    "llamadas_diarias": 1700,
    "tmo_diario": 321.47823529411767
  },
  {
    "fecha": "2025-09-21",
    "llamadas_diarias": 1072,
    "tmo_diario": 316.1063432835821
  },
  {
    "fecha": "2025-09-22",
    "llamadas_diarias": 1999,
    "tmo_diario": 352.47623811905953
  },
  {
    "fecha": "2025-09-23",
    "llamadas_diarias": 2120,
    "tmo_diario": 348.2344339622642
  },
  {
    "fecha": "2025-09-24",
    "llamadas_diarias": 2104,
    "tmo_diario": 342.38545627376425
  },
  {
    "fecha": "2025-09-25",
    "llamadas_diarias": 2201,
    "tmo_diario": 341.2348932303498
  },
  {
    "fecha": "2025-09-26",
    "llamadas_diarias": 2233,
    "tmo_diario": 341.9973130317958
  },
  {
    "fecha": "2025-09-27",
    "llamadas_diarias": 1682,
    "tmo_diario": 321.86682520808563
  },
  {
    "fecha": "2025-09-28",
    "llamadas_diarias": 1118,
    "tmo_diario": 316.1296958855098
  },
  {
    "fecha": "2025-09-29",
    "llamadas_diarias": 1992,
    "tmo_diario": 352.4874497991968
  },
  {
    "fecha": "2025-09-30",
    "llamadas_diarias": 2102,
    "tmo_diario": 348.22882968601334
  },
  {
    "fecha": "2025-10-01",
    "llamadas_diarias": 2063,
    "tmo_diario": 343.6844401357247
  },
  {
    "fecha": "2025-10-02",
    "llamadas_diarias": 2011,
    "tmo_diario": 350.1213326703133
  },
  {
    "fecha": "2025-10-03",
    "llamadas_diarias": 2032,
    "tmo_diario": 350.79133858267716
  },
  {
    "fecha": "2025-10-04",
    "llamadas_diarias": 1856,
    "tmo_diario": 322.7311422413793
  },
  {
    "fecha": "2025-10-05",
    "llamadas_diarias": 948,
    "tmo_diario": 321.81962025316454
  },
  {
    "fecha": "2025-10-06",
    "llamadas_diarias": 1996,
    "tmo_diario": 358.1292585170341
  },
  {
    "fecha": "2025-10-07",
    "llamadas_diarias": 2043,
    "tmo_diario": 345.40626529613314
  },
  {
    "fecha": "2025-10-08",
    "llamadas_diarias": 2043,
    "tmo_diario": 344.13803230543317
  },
  {
    "fecha": "2025-10-09",
    "llamadas_diarias": 2011,
    "tmo_diario": 350.36399801093984
  },
  {
    "fecha": "2025-10-10",
    "llamadas_diarias": 2041,
    "tmo_diario": 351.1019108280255
  },
  {
    "fecha": "2025-10-11",
    "llamadas_diarias": 1873,
    "tmo_diario": 322.87506673785373
  },
  {
    "fecha": "2025-10-12",
    "llamadas_diarias": 957,
    "tmo_diario": 322.13166144200625
  },
  {
    "fecha": "2025-10-13",
    "llamadas_diarias": 1998,
    "tmo_diario": 358.05455455455456
  },
  {
    "fecha": "2025-10-14",
    "llamadas_diarias": 2043,
    "tmo_diario": 345.45325501713165
  },
  {
    "fecha": "2025-10-15",
    "llamadas_diarias": 2042,
    "tmo_diario": 344.1983349657199
  },
  {
    "fecha": "2025-10-16",
    "llamadas_diarias": 2010,
    "tmo_diario": 350.3557213930348
  },
  {
    "fecha": "2025-10-17",
    "llamadas_diarias": 2041,
    "tmo_diario": 351.10436060754535
  },
  {
    "fecha": "2025-10-18",
    "llamadas_diarias": 1867,
    "tmo_diario": 322.87948580610606
  },
  {
    "fecha": "2025-10-19",
    "llamadas_diarias": 955,
    "tmo_diario": 322.130890052356
  },
  {
    "fecha": "2025-10-20",
    "llamadas_diarias": 1998,
    "tmo_diario": 358.13713713713713
  },
  {
    "fecha": "2025-10-21",
    "llamadas_diarias": 2043,
    "tmo_diario": 345.45325501713165
  },
  {
    "fecha": "2025-10-22",
    "llamadas_diarias": 2042,
    "tmo_diario": 344.1983349657199
  },
  {
    "fecha": "2025-10-23",
    "llamadas_diarias": 2010,
    "tmo_diario": 350.3557213930348
  },
  {
    "fecha": "2025-10-24",
    "llamadas_diarias": 2041,
    "tmo_diario": 351.10436060754535
  },
  {
    "fecha": "2025-10-25",
    "llamadas_diarias": 1868,
    "tmo_diario": 322.87312633832977
  },
  {
    "fecha": "2025-10-26",
    "llamadas_diarias": 956,
    "tmo_diario": 322.14016736401675
  },
  {
    "fecha": "2025-10-27",
    "llamadas_diarias": 1998,
    "tmo_diario": 358.13713713713713
  },
  {
    "fecha": "2025-10-28",
    "llamadas_diarias": 2043,
    "tmo_diario": 345.45325501713165
  },
  {
    "fecha": "2025-10-29",
    "llamadas_diarias": 2042,
    "tmo_diario": 344.1983349657199
  },
  {
    "fecha": "2025-10-30",
    "llamadas_diarias": 2010,
    "tmo_diario": 350.3557213930348
  },
  {
    "fecha": "2025-10-31",
    "llamadas_diarias": 2041,
    "tmo_diario": 351.10436060754535
  },
  {
    "fecha": "2025-11-01",
    "llamadas_diarias": 1814,
    "tmo_diario": 325.7778390297685
  },
  {
    "fecha": "2025-11-02",
    "llamadas_diarias": 1061,
    "tmo_diario": 316.1856738925542
  },
  {
    "fecha": "2025-11-03",
    "llamadas_diarias": 2096,
    "tmo_diario": 353.53387404580155
  },
  {
    "fecha": "2025-11-04",
    "llamadas_diarias": 2170,
    "tmo_diario": 341.02811059907833
  },
  {
    "fecha": "2025-11-05",
    "llamadas_diarias": 2075,
    "tmo_diario": 340.4963855421687
  },
  {
    "fecha": "2025-11-06",
    "llamadas_diarias": 2015,
    "tmo_diario": 347.54491315136477
  },
  {
    "fecha": "2025-11-07",
    "llamadas_diarias": 2116,
    "tmo_diario": 351.8993383742911
  },
  {
    "fecha": "2025-11-08",
    "llamadas_diarias": 1941,
    "tmo_diario": 325.51107676455433
  },
  {
    "fecha": "2025-11-09",
    "llamadas_diarias": 1100,
    "tmo_diario": 315.51454545454544
  },
  {
    "fecha": "2025-11-10",
    "llamadas_diarias": 2101,
    "tmo_diario": 352.98096144693005
  },
  {
    "fecha": "2025-11-11",
    "llamadas_diarias": 2164,
    "tmo_diario": 340.5332717190388
  },
  {
    "fecha": "2025-11-12",
    "llamadas_diarias": 2067,
    "tmo_diario": 340.4973391388486
  },
  {
    "fecha": "2025-11-13",
    "llamadas_diarias": 2011,
    "tmo_diario": 347.5788165091994
  },
  {
    "fecha": "2025-11-14",
    "llamadas_diarias": 2106,
    "tmo_diario": 351.8831908831909
  },
  {
    "fecha": "2025-11-15",
    "llamadas_diarias": 1931,
    "tmo_diario": 325.5116519937856
  },
  {
    "fecha": "2025-11-16",
    "llamadas_diarias": 1096,
    "tmo_diario": 315.45255474452557
  },
  {
    "fecha": "2025-11-17",
    "llamadas_diarias": 2100,
    "tmo_diario": 352.97333333333336
  },
  {
    "fecha": "2025-11-18",
    "llamadas_diarias": 2164,
    "tmo_diario": 340.5304990757856
  },
  {
    "fecha": "2025-11-19",
    "llamadas_diarias": 2069,
    "tmo_diario": 340.49492508458195
  },
  {
    "fecha": "2025-11-20",
    "llamadas_diarias": 2013,
    "tmo_diario": 347.5772478887233
  },
  {
    "fecha": "2025-11-21",
    "llamadas_diarias": 2107,
    "tmo_diario": 351.87470336971995
  },
  {
    "fecha": "2025-11-22",
    "llamadas_diarias": 1931,
    "tmo_diario": 325.5116519937856
  },
  {
    "fecha": "2025-11-23",
    "llamadas_diarias": 1096,
    "tmo_diario": 315.45255474452557
  },
  {
    "fecha": "2025-11-24",
    "llamadas_diarias": 1968,
    "tmo_diario": 354.2764227642276
  }
]